Metadata-Version: 1.0
Name: distributions-WC
Version: 0.1
Summary: Gaussian and binomial distributions
Home-page: UNKNOWN
Author: UNKNOWN
Author-email: wbchristerson@gmail.com
License: UNKNOWN
Platform: UNKNOWN
